paralleltask/__init__.py
paralleltask/__main__.py
paralleltask/cluster.cfg
paralleltask/kit.py
paralleltask/task_control.py
Paralleltask-0.2.3.dist-info/LICENSE
Paralleltask-0.2.3.dist-info/METADATA
Paralleltask-0.2.3.dist-info/WHEEL
Paralleltask-0.2.3.dist-info/entry_points.txt
Paralleltask-0.2.3.dist-info/top_level.txt
Paralleltask-0.2.3.dist-info/RECORD
