Metadata-Version: 2.1
Name: Paralleltask
Version: 0.2.3
Summary: A simple and lightweight parallel task engine
Home-page: https://github.com/moold/ParallelTask
Author: Hu Jiang
Author-email: mooldhu@gmail.com
License: GPLv3
Platform: UNKNOWN
Classifier: Programming Language :: Python :: 2
Classifier: Programming Language :: Python :: 3
Classifier: License :: OSI Approved :: GNU General Public License v3 (GPLv3)
License-File: LICENSE
Requires-Dist: psutil
